campari
campari.py
setup.py
version.py
campari.egg-info/PKG-INFO
campari.egg-info/SOURCES.txt
campari.egg-info/dependency_links.txt
campari.egg-info/requires.txt
campari.egg-info/top_level.txt