Metadata-Version: 1.1
Name: campari
Version: 0.1.1
Summary: Simple command-line pomodoro timer.
Home-page: https://github.com/iley/campari
Author: Ilya Strukov
Author-email: iley@iley.ru
License: UNKNOWN
Platform: UNKNOWN
Classifier: Development Status :: 3 - Alpha
Classifier: Environment :: Console
Classifier: License :: OSI Approved :: MIT License
Classifier: Programming Language :: Python :: 3.2
